{"id":1303,"title":"南米の海岸線を走る、コスモポリタンのラジオチューン","author":3,"date":"2017-12-10 01:46:51","artist":"The Anchors","album":"Saturdays of Thunder","albumImage":"1305","release":"20170928","trackList":"<ol>\n<li>Lose Me</li>\n<li>Downhill</li>\n<li>This Part Of Town</li>\n<li>Call</li>\n<li>Walk Away</li>\n</ol>","amazon":"","content":"<strong>The Anchors</strong>はチリの四人組ポストパンク・リバイバルバンド。国内に<strong>kmkms</strong>のボーカル寺田氏による同名のバンドがあるが、今日はそちらではなく、チリの方のレビューです。このバンド、おそらく今作が初めての音源であろうかと思われるのだが、ネット上で情報を拾うのが難しく（なぜかインスタとサンクラのアカウントしかないし、Youtubeに音源は上がってるけど再生回数も百前後レベル）詳細はわからない。マジで情報が拾えないのでジャケットの画像もサンクラからスクショしてきた。ただ<strong>Franz Ferdinand</strong>もだし、<strong>The Fratellis</strong>とか、言うまでもなく<strong>Arctic Monkeys</strong>とかその手のUKポストパンクリバイバルバンドへのリスペクトがゴリゴリに出てて、しかもそれがUKのバンドならそんなに気にもしなかったと思うんだけど、チリのバンドっていうから思わず手を伸ばしてしまった。チリってどんなバンドがいるのかなとか想像もできないわけだけど、もはやネットの海に飛び込めば国境もお国柄も関係ない時代、どこの国からどんな音楽が出てきても驚くようなことではないのかもしれない。ちなみにチリの公用語はスペイン語とのことだが、それに関しても違和感ないナルい英語を使いこなすし、案外英語圏で生活していたメンバーがいたりとかなのかもしれない。\n\n聞いてる感じだと、バンドのコンポーザーであろうギターボーカルがなかなかポストパンク好きとしてのカラーを強く出しつつ、他のメンバーは彼に追従する形のようだ。絶妙に時々下手なドラムとか、リードギターのヘナっとしたギターリフもなかなか愛せる。そしてその実結構曲がいいのだ。正直ポストパンクリバイバル界隈ってかなりフォーマットが画一的なように思えて、リフもコード進行もどっかで聞いたことあるなって思うバンドはたくさんいるわけで、その例には残念ながらもれないわけだけど、しっかりとジャンル愛のある楽曲はなかなか侮れない。#1 \"Lose Me\"のクリーントーンのニヒルなコードリフや#2 \"Downhill\"のドライブ感の強いコードストローク、そしてやっぱり外せないツインギターのギターリフがダンサブルに転がる#3 \"This Part Of Town\"では痩せたクリーンギターのへなちょこなチョーキングが癖になる。かたや#4 \"Call\"ではコーラスギターでミドルテンポに、哀愁を漂わせつつ、ラストナンバー#5 \"Walk Away\"はサビではじける緩急がライブでは盛り上がりそうだ。\n\nジャンルへの愛からくる「型」の模倣って、すごく純粋な感情だなと僕は思っていてそういうのが好きで、今回はそんなバンドの紹介。UKポストパンクリバイバル好き是非聞いて、僕以上に正当な評価を下してください。\n\n&nbsp;\n\n<iframe src=\"https://w.soundcloud.com/player/?url=https%3A//api.soundcloud.com/playlists/355874870&amp;color=%23ff5500&amp;auto_play=false&amp;hide_related=false&amp;show_comments=true&amp;show_user=true&amp;show_reposts=false&amp;show_teaser=true&amp;visual=true\" width=\"100%\" height=\"300\" frameborder=\"no\" scrolling=\"no\"></iframe>"}
